ArrowStack-0.1.dev0.dist-info/DESCRIPTION.rst
ArrowStack-0.1.dev0.dist-info/METADATA
ArrowStack-0.1.dev0.dist-info/RECORD
ArrowStack-0.1.dev0.dist-info/WHEEL
ArrowStack-0.1.dev0.dist-info/entry_points.txt
ArrowStack-0.1.dev0.dist-info/metadata.json
ArrowStack-0.1.dev0.dist-info/top_level.txt
arrow/Request.py
arrow/Response.py
arrow/__init__.py
arrow/application.py
arrow/view.py
arrow/middleware/__init__.py
arrow/middleware/crossorigin.py
arrowstack/Dockerfile.tpl
arrowstack/__init__.py
arrowstack/nginx.conf
arrowstack/release.py
