Metadata-Version: 2.0
Name: ArrowStack
Version: 0.1.dev0
Summary: UNKNOWN
Home-page: UNKNOWN
Author: UNKNOWN
Author-email: UNKNOWN
License: Creative Commons Attribution-Noncommercial-Share Alike license
Platform: UNKNOWN
Requires-Dist: Jinja2
Requires-Dist: docker
Requires-Dist: gunicorn
Requires-Dist: pymist
Requires-Dist: routes
Requires-Dist: webob
